README.txt
setup.cfg
setup.py
Products/__init__.py
Products.DimensionWidget.egg-info/PKG-INFO
Products.DimensionWidget.egg-info/SOURCES.txt
Products.DimensionWidget.egg-info/dependency_links.txt
Products.DimensionWidget.egg-info/entry_points.txt
Products.DimensionWidget.egg-info/namespace_packages.txt
Products.DimensionWidget.egg-info/not-zip-safe
Products.DimensionWidget.egg-info/requires.txt
Products.DimensionWidget.egg-info/top_level.txt
Products/DimensionWidget/__init__.py
Products/DimensionWidget/config.py
Products/DimensionWidget/configure.zcml
Products/DimensionWidget/validator.py
Products/DimensionWidget/widget.py
Products/DimensionWidget/i18n/DimensionWidget-de-plone.po
Products/DimensionWidget/i18n/DimensionWidget-fr-plone.po
Products/DimensionWidget/profiles/default/metadata.xml
Products/DimensionWidget/profiles/default/skins.xml
Products/DimensionWidget/skins/dimension_widget/dimension_widget.pt
docs/HISTORY.txt