Metadata-Version: 1.0
Name: Products.DimensionWidget
Version: 2.0b3
Summary: Provides an archetypes widget to store a dimension (width and height) in a StringField
Home-page: http://raptus.com
Author: Raptus AG
Author-email: dev@raptus.com
License: GPL
Platform: UNKNOWN
Classifier: Programming Language :: Python
Classifier: Topic :: Software Development :: Libraries :: Python Modules
